certbot_dns_onecloud-0.1.0.dist-info/dependency_links.txt
certbot_dns_onecloud-0.1.0.dist-info/entry_points.txt
certbot_dns_onecloud-0.1.0.dist-info/METADATA
certbot_dns_onecloud-0.1.0.dist-info/top_level.txt
certbot_dns_onecloud-0.1.0.dist-info/WHEEL
certbot_dns_onecloud/dns_onecloud.py
certbot_dns_onecloud/__init__.py
certbot_dns_onecloud/client.py
certbot_dns_onecloud-0.1.0.dist-info/LICENSE
certbot_dns_onecloud-0.1.0.dist-info/RECORD